SEOTool/__init__.py
SEOTool/module.py
SEOTool-1.9.dist-info/LICENSE
SEOTool-1.9.dist-info/METADATA
SEOTool-1.9.dist-info/WHEEL
SEOTool-1.9.dist-info/top_level.txt
SEOTool-1.9.dist-info/RECORD
