Metadata-Version: 2.2
Name: SEOTool
Version: 1.9
Summary: Some scripts for Baidu SEO purpose
Home-page: 
Author: Jiayu Tan
Author-email: jtan010@uottawa.ca
Classifier: Programming Language :: Python :: 3
Classifier: License :: OSI Approved :: MIT License
Classifier: Operating System :: OS Independent
License-File: LICENSE
Requires-Dist: fake-useragent>=1.5.1
Requires-Dist: requests>=2.32.3
Requires-Dist: lxml>=5.3.0
Dynamic: author
Dynamic: author-email
Dynamic: classifier
Dynamic: description
Dynamic: description-content-type
Dynamic: requires-dist
Dynamic: summary
